awslabs/__init__.py
awslabs/terraform_mcp_server/__init__.py
awslabs/terraform_mcp_server/server.py
awslabs/terraform_mcp_server/impl/resources/__init__.py
awslabs/terraform_mcp_server/impl/resources/terraform_aws_provider_resources_listing.py
awslabs/terraform_mcp_server/impl/resources/terraform_awscc_provider_resources_listing.py
awslabs/terraform_mcp_server/impl/tools/__init__.py
awslabs/terraform_mcp_server/impl/tools/execute_terraform_command.py
awslabs/terraform_mcp_server/impl/tools/execute_terragrunt_command.py
awslabs/terraform_mcp_server/impl/tools/run_checkov_scan.py
awslabs/terraform_mcp_server/impl/tools/search_aws_provider_docs.py
awslabs/terraform_mcp_server/impl/tools/search_awscc_provider_docs.py
awslabs/terraform_mcp_server/impl/tools/search_specific_aws_ia_modules.py
awslabs/terraform_mcp_server/impl/tools/search_user_provided_module.py
awslabs/terraform_mcp_server/impl/tools/utils.py
awslabs/terraform_mcp_server/models/__init__.py
awslabs/terraform_mcp_server/models/models.py
awslabs/terraform_mcp_server/scripts/generate_aws_provider_resources.py
awslabs/terraform_mcp_server/scripts/generate_awscc_provider_resources.py
awslabs/terraform_mcp_server/scripts/scrape_aws_terraform_best_practices.py
awslabs/terraform_mcp_server/static/AWSCC_PROVIDER_RESOURCES.md
awslabs/terraform_mcp_server/static/AWS_PROVIDER_RESOURCES.md
awslabs/terraform_mcp_server/static/AWS_TERRAFORM_BEST_PRACTICES.md
awslabs/terraform_mcp_server/static/MCP_INSTRUCTIONS.md
awslabs/terraform_mcp_server/static/TERRAFORM_WORKFLOW_GUIDE.md
awslabs/terraform_mcp_server/static/__init__.py
awslabs_terraform_mcp_server-1.0.14.dist-info/METADATA
awslabs_terraform_mcp_server-1.0.14.dist-info/WHEEL
awslabs_terraform_mcp_server-1.0.14.dist-info/entry_points.txt
awslabs_terraform_mcp_server-1.0.14.dist-info/RECORD
