Metadata-Version: 2.4
Name: awslabs.terraform-mcp-server
Version: 1.0.14
Summary: An AWS Labs Model Context Protocol (MCP) server for terraform
Requires-Python: >=3.10
Requires-Dist: asteval>=1.0.6
Requires-Dist: beautifulsoup4>=4.12.0
Requires-Dist: checkov>=3.2.402
Requires-Dist: loguru>=0.7.0
Requires-Dist: mcp[cli]>=1.23.0
Requires-Dist: playwright>=1.40.0
Requires-Dist: pydantic>=2.10.6
Requires-Dist: pypdf2>=3.0.0
Requires-Dist: requests>=2.31.0
